LICENSE.txt
README.md
setup.cfg
setup.py
brl_conversor/__init__.py
brl_conversor/conversor.py
brl_conversor.egg-info/PKG-INFO
brl_conversor.egg-info/SOURCES.txt
brl_conversor.egg-info/dependency_links.txt
brl_conversor.egg-info/top_level.txt