Metadata-Version: 1.1
Name: brl-conversor
Version: 1.0.0
Summary: A simple converter for BRL from other currencies like USD and EUR.
Home-page: UNKNOWN
Author: José Almir
Author-email: resilientcod@gmail.com
License: MIT
Platform: UNKNOWN
Classifier: Development Status :: 5 - Production/Stable
Classifier: Intended Audience :: Developers
Classifier: License :: OSI Approved :: MIT License
Classifier: Natural Language :: Portuguese (Brazilian)
Classifier: Operating System :: OS Independent
Classifier: Topic :: Software Development :: Internationalization
Classifier: Topic :: Scientific/Engineering :: Physics
